alist/AList.py
alist/__init__.py
alist/data/__init__.py
alist/data/image.py
alist/data/mal.py
alist/data/mal_export.py
alist/data/mal_import.py
alist/data/myanimelist.py
alist/data/mymangalist.py
alist/data/translation.py
alist/pages/__init__.py
alist/pages/accueil.py
alist/pages/anime.py
alist/pages/list_anime.py
alist/pages/list_manga.py
alist/pages/manga.py
alist/pages/menu.py
alist/pages/modif_anime.py
alist/pages/modif_manga.py
alist/pages/my_anime.py
alist/pages/my_manga.py
alist/pages/parameters.py
alist/pages/right_page.py
alist/utils/__init__.py
alist/utils/config.py
alist/utils/scroll_frame.py
alist/utils/utils.py
AList-2.0.0.dist-info/LICENSE.md
AList-2.0.0.dist-info/METADATA
AList-2.0.0.dist-info/WHEEL
AList-2.0.0.dist-info/entry_points.txt
AList-2.0.0.dist-info/top_level.txt
AList-2.0.0.dist-info/RECORD
